qte_parts_crawler/__init__.py
qte_parts_crawler/main.py
qte_parts_crawler/utils/__init__.py
qte_parts_crawler/utils/actions.py
qte_parts_crawler/utils/admin_server_api.py
qte_parts_crawler/utils/bypass_recaptcha.py
qte_parts_crawler/utils/helpers.py
qte_parts_crawler-0.1.5.dist-info/licenses/LICENSE
qte_parts_crawler-0.1.5.dist-info/METADATA
qte_parts_crawler-0.1.5.dist-info/WHEEL
qte_parts_crawler-0.1.5.dist-info/entry_points.txt
qte_parts_crawler-0.1.5.dist-info/top_level.txt
qte_parts_crawler-0.1.5.dist-info/RECORD
