Metadata-Version: 2.4
Name: qte-parts-crawler
Version: 0.1.5
Summary: A web crawler for QTE parts data
Home-page: https://github.com/yourusername/qte-parts-crawler
Author: Allen Yan
Author-email: wsyanligang@gmail.com
Classifier: Programming Language :: Python :: 3
Classifier: Topic :: Internet :: WWW/HTTP :: Indexing/Search
Classifier: License :: OSI Approved :: MIT License
Requires-Python: >=3.6
License-File: LICENSE
Requires-Dist: requests
Requires-Dist: beautifulsoup4
Requires-Dist: lxml
Requires-Dist: 2captcha-python
Requires-Dist: certifi
Requires-Dist: charset-normalizer
Requires-Dist: idna
Requires-Dist: selenium
Requires-Dist: urllib3
Requires-Dist: websocket-client
Requires-Dist: Flask
Requires-Dist: gunicorn
Requires-Dist: Werkzeug
Requires-Dist: dotenv
Dynamic: author
Dynamic: author-email
Dynamic: classifier
Dynamic: description
Dynamic: description-content-type
Dynamic: home-page
Dynamic: license-file
Dynamic: requires-dist
Dynamic: requires-python
Dynamic: summary
